{
  "phase": "R5",
  "stepsPerScenario": 64,
  "scenarioCount": 10,
  "checkpointDigest": 2072020786,
  "checkpoints": [
    {
      "id": "wl1-map-0",
      "mapIndex": 0,
      "mapName": "Wolf1 Map1",
      "seedHex": "0x940ff88b",
      "stepCount": 64,
      "traceHash": 527718941,
      "stepDigest": 207629622,
      "finalSnapshotHash": 2074822916,
      "finalFrameHash": 2562710687,
      "finalTick": 289
    },
    {
      "id": "wl1-map-1",
      "mapIndex": 1,
      "mapName": "Wolf1 Map2",
      "seedHex": "0xa0048769",
      "stepCount": 64,
      "traceHash": 555936219,
      "stepDigest": 2084827678,
      "finalSnapshotHash": 2822532288,
      "finalFrameHash": 18930441,
      "finalTick": 275
    },
    {
      "id": "wl1-map-2",
      "mapIndex": 2,
      "mapName": "Wolf1 Map3",
      "seedHex": "0xc642f47f",
      "stepCount": 64,
      "traceHash": 4268143392,
      "stepDigest": 3351168622,
      "finalSnapshotHash": 2241448402,
      "finalFrameHash": 970763770,
      "finalTick": 310
    },
    {
      "id": "wl1-map-3",
      "mapIndex": 3,
      "mapName": "Wolf1 Map4",
      "seedHex": "0x92520d01",
      "stepCount": 64,
      "traceHash": 2738060511,
      "stepDigest": 355537682,
      "finalSnapshotHash": 2552004031,
      "finalFrameHash": 3726527312,
      "finalTick": 309
    },
    {
      "id": "wl1-map-4",
      "mapIndex": 4,
      "mapName": "Wolf1 Map5",
      "seedHex": "0xc6dada9b",
      "stepCount": 64,
      "traceHash": 3979508241,
      "stepDigest": 3353201094,
      "finalSnapshotHash": 984902740,
      "finalFrameHash": 3731646177,
      "finalTick": 311
    },
    {
      "id": "wl1-map-5",
      "mapIndex": 5,
      "mapName": "Wolf1 Map6",
      "seedHex": "0x0cfd9919",
      "stepCount": 64,
      "traceHash": 263571243,
      "stepDigest": 3917925302,
      "finalSnapshotHash": 3476235596,
      "finalFrameHash": 688371615,
      "finalTick": 301
    },
    {
      "id": "wl1-map-6",
      "mapIndex": 6,
      "mapName": "Wolf1 Map7",
      "seedHex": "0x8c4b76f7",
      "stepCount": 64,
      "traceHash": 1510834763,
      "stepDigest": 1722998814,
      "finalSnapshotHash": 2964642197,
      "finalFrameHash": 1279857058,
      "finalTick": 305
    },
    {
      "id": "wl1-map-7",
      "mapIndex": 7,
      "mapName": "Wolf1 Map8",
      "seedHex": "0xc40ef5e1",
      "stepCount": 64,
      "traceHash": 4250110686,
      "stepDigest": 1789165282,
      "finalSnapshotHash": 1914352026,
      "finalFrameHash": 2893594326,
      "finalTick": 314
    },
    {
      "id": "wl1-map-8",
      "mapIndex": 8,
      "mapName": "Wolf1 Boss",
      "seedHex": "0xf12d3aa7",
      "stepCount": 64,
      "traceHash": 290375296,
      "stepDigest": 623658182,
      "finalSnapshotHash": 2037816984,
      "finalFrameHash": 1440653374,
      "finalTick": 284
    },
    {
      "id": "wl1-map-9",
      "mapIndex": 9,
      "mapName": "Wolf1 Secret",
      "seedHex": "0xbfb46999",
      "stepCount": 64,
      "traceHash": 4055919918,
      "stepDigest": 1755659098,
      "finalSnapshotHash": 4031619953,
      "finalFrameHash": 160045771,
      "finalTick": 256
    }
  ]
}
