{
  "phase": "R5",
  "stepsPerScenario": 64,
  "scenarioCount": 10,
  "checkpointDigest": 3774325772,
  "checkpoints": [
    {
      "id": "wl1-map-0",
      "mapIndex": 0,
      "mapName": "Wolf1 Map1",
      "seedHex": "0x940ff88b",
      "stepCount": 64,
      "traceHash": 1439280547,
      "stepDigest": 1339399298,
      "finalSnapshotHash": 3875809512,
      "finalFrameHash": 3685309779,
      "finalTick": 289
    },
    {
      "id": "wl1-map-1",
      "mapIndex": 1,
      "mapName": "Wolf1 Map2",
      "seedHex": "0xa0048769",
      "stepCount": 64,
      "traceHash": 2417765535,
      "stepDigest": 2536284630,
      "finalSnapshotHash": 2702032414,
      "finalFrameHash": 2953094395,
      "finalTick": 275
    },
    {
      "id": "wl1-map-2",
      "mapIndex": 2,
      "mapName": "Wolf1 Map3",
      "seedHex": "0xc642f47f",
      "stepCount": 64,
      "traceHash": 824822504,
      "stepDigest": 3719741878,
      "finalSnapshotHash": 3160445606,
      "finalFrameHash": 520099782,
      "finalTick": 310
    },
    {
      "id": "wl1-map-3",
      "mapIndex": 3,
      "mapName": "Wolf1 Map4",
      "seedHex": "0x92520d01",
      "stepCount": 64,
      "traceHash": 61152655,
      "stepDigest": 1576609582,
      "finalSnapshotHash": 3811326680,
      "finalFrameHash": 261103239,
      "finalTick": 309
    },
    {
      "id": "wl1-map-4",
      "mapIndex": 4,
      "mapName": "Wolf1 Map5",
      "seedHex": "0xc6dada9b",
      "stepCount": 64,
      "traceHash": 1681539419,
      "stepDigest": 3189212786,
      "finalSnapshotHash": 144361552,
      "finalFrameHash": 2520469965,
      "finalTick": 311
    },
    {
      "id": "wl1-map-5",
      "mapIndex": 5,
      "mapName": "Wolf1 Map6",
      "seedHex": "0x0cfd9919",
      "stepCount": 64,
      "traceHash": 2683325867,
      "stepDigest": 2471031262,
      "finalSnapshotHash": 2212991624,
      "finalFrameHash": 2137182131,
      "finalTick": 301
    },
    {
      "id": "wl1-map-6",
      "mapIndex": 6,
      "mapName": "Wolf1 Map7",
      "seedHex": "0x8c4b76f7",
      "stepCount": 64,
      "traceHash": 3421669825,
      "stepDigest": 1136021658,
      "finalSnapshotHash": 3314854545,
      "finalFrameHash": 3357589614,
      "finalTick": 305
    },
    {
      "id": "wl1-map-7",
      "mapIndex": 7,
      "mapName": "Wolf1 Map8",
      "seedHex": "0xc40ef5e1",
      "stepCount": 64,
      "traceHash": 4250110686,
      "stepDigest": 1789165282,
      "finalSnapshotHash": 1914352026,
      "finalFrameHash": 2893594326,
      "finalTick": 314
    },
    {
      "id": "wl1-map-8",
      "mapIndex": 8,
      "mapName": "Wolf1 Boss",
      "seedHex": "0xf12d3aa7",
      "stepCount": 64,
      "traceHash": 2882514364,
      "stepDigest": 2453418862,
      "finalSnapshotHash": 3695816992,
      "finalFrameHash": 2715088646,
      "finalTick": 284
    },
    {
      "id": "wl1-map-9",
      "mapIndex": 9,
      "mapName": "Wolf1 Secret",
      "seedHex": "0xbfb46999",
      "stepCount": 64,
      "traceHash": 1718773292,
      "stepDigest": 2072805366,
      "finalSnapshotHash": 2042951207,
      "finalFrameHash": 2194642109,
      "finalTick": 256
    }
  ]
}
